SentimentDetection.py
Tools.py
__init__.py
nlp_for_mlf-0.0.6.dist-info/LICENSE
nlp_for_mlf-0.0.6.dist-info/METADATA
nlp_for_mlf-0.0.6.dist-info/WHEEL
nlp_for_mlf-0.0.6.dist-info/top_level.txt
nlp_for_mlf-0.0.6.dist-info/RECORD
