Metadata-Version: 2.1
Name: nlp-for-mlf
Version: 0.0.6
Summary: NLP package
Home-page: https://github.com/BenjaminFranline
Author: MLF Team
Author-email: MLF team <support@mylittlefintech.com>
License: Copyright (c) 2018 The Python Packaging Authority        
Project-URL: Homepage, https://olean.visualstudio.com/Editis/_git/Complaints?path=/awssejer
Project-URL: Bug Tracker, https://olean.visualstudio.com/Editis/_git/Complaints?path=/awssejer/issues
Keywords: nlp
Classifier: Programming Language :: Python :: 3
Classifier: License :: OSI Approved :: MIT License
Classifier: Operating System :: OS Independent
Requires-Python: >=3.9, <4
License-File: LICENSE
Requires-Dist: torch
Requires-Dist: transformers
Requires-Dist: numpy (>=1.14.5)
Requires-Dist: matplotlib (>=2.2.0)
